ioc_fanger/__init__.py
ioc_fanger/ioc_fanger.py
ioc_fanger/regexes_defang.py
ioc_fanger/regexes_fang.py
ioc_fanger-4.2.1.dist-info/LICENSE
ioc_fanger-4.2.1.dist-info/METADATA
ioc_fanger-4.2.1.dist-info/WHEEL
ioc_fanger-4.2.1.dist-info/entry_points.txt
ioc_fanger-4.2.1.dist-info/top_level.txt
ioc_fanger-4.2.1.dist-info/zip-safe
ioc_fanger-4.2.1.dist-info/RECORD
