Metadata-Version: 2.1
Name: ioc_fanger
Version: 4.2.1
Summary: Python package to defang and fang indicators of compromise from text.
Home-page: https://github.com/ioc-fang/ioc_fanger
Author: Floyd Hightower
Author-email: 
License: MIT
Project-URL: Documentation, https://github.com/ioc-fang/ioc-fanger
Project-URL: Say Thanks!, https://saythanks.io/to/floyd.hightower27%40gmail.com
Project-URL: Source, https://github.com/ioc-fang/ioc-fanger
Project-URL: Tracker, https://github.com/ioc-fang/ioc-fanger/issues
Project-URL: PyPi, https://pypi.org/project/ioc-fanger/
Project-URL: CI, https://travis-ci.com/ioc-fang/ioc-fanger.svg?branch=main
Project-URL: Changelog, https://github.com/ioc-fang/ioc-fanger/blob/main/CHANGELOG.md
Keywords: iocs,indicators of compromise,threat intelligence,malware,threat hunting,observables,fanging,defanging,fang,defang,refang
Classifier: Development Status :: 5 - Production/Stable
Classifier: Intended Audience :: Developers
Classifier: License :: OSI Approved :: MIT License
Classifier: Natural Language :: English
Classifier: Programming Language :: Python :: 3
Classifier: Programming Language :: Python :: 3.7
Classifier: Programming Language :: Python :: 3.8
Classifier: Programming Language :: Python :: 3.9
License-File: LICENSE
